LICENSE.txt
MANIFEST.in
README.md
setup.cfg
setup.py
events_dock/__init__.py
events_dock/__main__.py
events_dock/app.py
events_dock/components.py
events_dock/config.ini
events_dock/handlers.py
events_dock/mappers.py
events_dock/models.py
events_dock/threads.py
events_dock/utils.py
events_dock.egg-info/PKG-INFO
events_dock.egg-info/SOURCES.txt
events_dock.egg-info/dependency_links.txt
events_dock.egg-info/entry_points.txt
events_dock.egg-info/requires.txt
events_dock.egg-info/top_level.txt